drb/topics/safe/__init__.py
drb/topics/safe/_version.py
drb/topics/safe/cortex.yml
drb_topic_safe-1.3.0.dist-info/LICENCE.txt
drb_topic_safe-1.3.0.dist-info/METADATA
drb_topic_safe-1.3.0.dist-info/WHEEL
drb_topic_safe-1.3.0.dist-info/entry_points.txt
drb_topic_safe-1.3.0.dist-info/top_level.txt
drb_topic_safe-1.3.0.dist-info/RECORD
